{
  "type": "Feature",
  "properties": {
    "gn:admin1_code":"21",
    "gn:admin2_code":"2111.0",
    "gn:asciiname":"Haugen",
    "gn:cc2":"SJ",
    "gn:country_code":"SJ",
    "gn:dem":8,
    "gn:feature_class":"P",
    "gn:feature_code":"PPL",
    "gn:name":"Haugen",
    "gn:population":0,
    "gn:timezone":"Arctic/Longyearbyen",
    "iso:country":"SJ",
    "name:und_x_variant":[
        "Navarhaugen",
        "Funksjon\u00e6rbyen",
        "Haugen"
    ],
    "wof:name":"Haugen",
    "wof:placetype":"locality"
},
  "geometry": {"coordinates":[15.63333,78.21666999999999],"type":"Point"}
}